{
  "$schema": "../../../schemas/v3/table.v3.schema.json",
  "id": "517d50a3-960f-42ce-810f-3b126398d7b1",
  "name": "コンテンツパック",
  "description": "分野別学習コンテンツのパッケージ管理テーブル。汎用 / IT エンジニア / ビジネス / 旅行 等の分野ごとにパックを定義する。namespace_ref で english-learning 拡張に紐付けることで動的コンテンツ追加を表現する。",
  "maturity": "draft",
  "createdAt": "2026-05-04T00:00:00.000Z",
  "updatedAt": "2026-05-04T00:00:00.000Z",
  "physicalName": "content_packs",
  "category": "マスタ",
  "comment": "コンテンツパックマスタ。分野別の学習コンテンツをパッケージ化して管理する。",
  "columns": [
    {
      "id": "col-id",
      "no": 1,
      "physicalName": "id",
      "name": "パックID",
      "dataType": "BIGINT",
      "notNull": true,
      "primaryKey": true,
      "autoIncrement": true,
      "comment": "サロゲートキー (自動採番)"
    },
    {
      "id": "col-name",
      "no": 2,
      "physicalName": "name",
      "name": "パック名",
      "dataType": "VARCHAR",
      "length": 200,
      "notNull": true,
      "comment": "パックの表示名 (例: 「IT エンジニア英語」「ビジネス英語」)"
    },
    {
      "id": "col-slug",
      "no": 3,
      "physicalName": "slug",
      "name": "スラッグ",
      "dataType": "VARCHAR",
      "length": 100,
      "notNull": true,
      "unique": true,
      "comment": "URL / API 用識別子 (例: general, it-engineer, business)"
    },
    {
      "id": "col-description",
      "no": 4,
      "physicalName": "description",
      "name": "説明",
      "dataType": "TEXT",
      "notNull": false,
      "comment": "パックの概要説明 (コンテンツパック一覧画面で表示)"
    },
    {
      "id": "col-thumbnail-url",
      "no": 5,
      "physicalName": "thumbnail_url",
      "name": "サムネイル URL",
      "dataType": "VARCHAR",
      "length": 500,
      "notNull": false,
      "comment": "一覧カード表示用サムネイル画像 URL"
    },
    {
      "id": "col-namespace-ref",
      "no": 6,
      "physicalName": "namespace_ref",
      "name": "拡張 namespace 参照",
      "dataType": "VARCHAR",
      "length": 200,
      "notNull": false,
      "comment": "拡張定義への参照 (例: english-learning)。動的コンテンツパックと拡張 namespace を紐付ける",
      "description": "null の場合は汎用パック (拡張なし)。拡張パックの場合は namespace 識別子を格納し、拡張定義ファイルを動的ロードする際の参照キーとして使用する。"
    },
    {
      "id": "col-is-active",
      "no": 7,
      "physicalName": "is_active",
      "name": "公開中フラグ",
      "dataType": "BOOLEAN",
      "notNull": true,
      "defaultValue": "TRUE",
      "comment": "FALSE で非公開 (論理削除)"
    },
    {
      "id": "col-created-at",
      "no": 8,
      "physicalName": "created_at",
      "name": "登録日時",
      "dataType": "TIMESTAMP",
      "notNull": true,
      "defaultValue": "CURRENT_TIMESTAMP",
      "comment": "レコード作成日時"
    }
  ],
  "constraints": [
    {
      "id": "uq-slug",
      "kind": "unique",
      "physicalName": "uq_content_packs_slug",
      "columnIds": ["col-slug"],
      "description": "スラッグの一意制約 (URL / API で一意識別するため)"
    }
  ],
  "indexes": [
    {
      "id": "idx-slug",
      "physicalName": "idx_content_packs_slug",
      "columns": [{ "columnId": "col-slug", "order": "asc" }],
      "unique": true,
      "method": "btree",
      "description": "スラッグ検索インデックス"
    },
    {
      "id": "idx-is-active",
      "physicalName": "idx_content_packs_is_active",
      "columns": [{ "columnId": "col-is-active", "order": "asc" }],
      "method": "btree",
      "description": "公開中パック絞り込みインデックス"
    }
  ]
}
