{
  "$schema": "https://json-schema.org/draft/2020-12/schema",
  "$id": "https://raw.githubusercontent.com/csilost2001/html-designer/main/schemas/v2/process-flow.v2.schema.json",
  "type": "object",
  "required": [
    "id",
    "name",
    "kind",
    "description",
    "actions",
    "createdAt",
    "updatedAt"
  ],
  "additionalProperties": false,
  "properties": {
    "id": {
      "$ref": "common.v2.schema.json#/$defs/Uuid"
    },
    "name": {
      "type": "string"
    },
    "screenId": {
      "$ref": "common.v2.schema.json#/$defs/Uuid"
    },
    "description": {
      "$ref": "common.v2.schema.json#/$defs/Description"
    },
    "apiVersion": {
      "description": "API バージョン識別子 (#423 B-6)。例: \"v1\", \"2026-04-25\"",
      "type": "string"
    },
    "maturity": {
      "$ref": "common.v2.schema.json#/$defs/MaturityLevel"
    },
    "mode": {
      "$ref": "common.v2.schema.json#/$defs/ProcessMode"
    },
    "sla": {
      "$ref": "#/$defs/Sla"
    },
    "health": {
      "$ref": "#/$defs/HealthCheckGroup"
    },
    "readiness": {
      "$ref": "#/$defs/ReadinessCheckGroup"
    },
    "resources": {
      "$ref": "#/$defs/ResourceRequirements"
    },
    "errorCatalog": {
      "description": "エラーコードカタログ (#253)。キーは errorCode (例: STOCK_SHORTAGE)。affectedRowsCheck.errorCode / BranchConditionVariant.errorCode から参照される",
      "type": "object",
      "additionalProperties": {
        "$ref": "#/$defs/ErrorCatalogEntry"
      }
    },
    "externalSystemCatalog": {
      "description": "外部システムカタログ (#261 v1.3)。キー: systemId (例: \"stripe\")。ExternalSystemStep.systemRef から参照",
      "type": "object",
      "additionalProperties": {
        "$ref": "#/$defs/ExternalSystemCatalogEntry"
      }
    },
    "ambientVariables": {
      "description": "Ambient 変数カタログ (#261 v1.4)。ミドルウェア由来 (@requestId, @traceId, @fieldErrors 等) を宣言",
      "type": "array",
      "items": {
        "$ref": "#/$defs/StructuredField"
      }
    },
    "ambientOverrides": {
      "description": "規約カタログ defaults へのフロー固有例外 (#369)。未指定時は data/conventions/catalog.json の default:true エントリを全項目で継承。キーはカタログカテゴリ名 (例: \"currency\", \"scope.timezone\")、値は @conv.* 参照文字列またはリテラル値",
      "type": "object",
      "additionalProperties": {
        "type": "string"
      }
    },
    "secretsCatalog": {
      "description": "Secrets カタログ (#261 v1.6 / #414 で values 拡張)。秘匿値のメタデータ (取得元・ローテーション・環境別参照式)。値そのものは含まない",
      "type": "object",
      "additionalProperties": {
        "$ref": "#/$defs/SecretRef"
      }
    },
    "envVarsCatalog": {
      "description": "環境変数カタログ (#414)。Power Platform Environment Variables 由来。型 + 環境別 values + default を持ち、@env.<KEY> で式から参照される。dev/staging/prod 等の環境で値を切り替える ALM 対応",
      "type": "object",
      "additionalProperties": {
        "$ref": "#/$defs/EnvVarEntry"
      }
    },
    "domainsCatalog": {
      "description": "Domain 概念カタログ (#422 P2-1 / GeneXus 由来)。キー: ドメイン名 (例: \"EmailAddress\", \"Quantity\")。StructuredField.domainRef から参照される。型・制約・UI ヒントを 1 箇所に集約し DRY 化する",
      "type": "object",
      "additionalProperties": {
        "$ref": "#/$defs/DomainDef"
      }
    },
    "functionsCatalog": {
      "description": "組み込み関数カタログ (#422 P2-5 / Wagby 由来)。キー: 関数名 (例: \"formatCurrency\", \"calcAge\")。@fn.* 参照形式で式から呼び出される",
      "type": "object",
      "additionalProperties": {
        "$ref": "#/$defs/FunctionDef"
      }
    },
    "eventsCatalog": {
      "description": "イベント pub/sub カタログ (#423 B-1)。キー: トピック名。EventPublishStep / EventSubscribeStep から参照される",
      "type": "object",
      "additionalProperties": {
        "$ref": "#/$defs/EventDef"
      }
    },
    "glossary": {
      "description": "ビジネス用語集 (#423 B-3)。キー: 用語名。ドメイン固有語・略語の定義と別名を集約する",
      "type": "object",
      "additionalProperties": {
        "$ref": "#/$defs/GlossaryEntry"
      }
    },
    "decisions": {
      "description": "ADR / 設計判断ログ (#423 B-5)。アーキテクチャ上の決定とその根拠・影響を記録する",
      "type": "array",
      "items": {
        "$ref": "#/$defs/DecisionRecord"
      }
    },
    "markers": {
      "description": "マーカー (#261)。人間が designer で付けた指示・質問・TODO・チャット。AI が読み取り resolvedAt で解決",
      "type": "array",
      "items": {
        "$ref": "#/$defs/Marker"
      }
    },
    "testScenarios": {
      "type": "array",
      "items": {
        "$ref": "#/$defs/TestScenario"
      }
    },
    "actions": {
      "type": "array",
      "items": {
        "$ref": "#/$defs/ActionDefinition"
      }
    },
    "createdAt": {
      "$ref": "common.v2.schema.json#/$defs/Timestamp"
    },
    "updatedAt": {
      "$ref": "common.v2.schema.json#/$defs/Timestamp"
    },
    "kind": {
      "$ref": "#/$defs/ProcessFlowKind"
    },
    "$schema": {
      "type": "string"
    },
    "version": {
      "$ref": "common.v2.schema.json#/$defs/SemVer"
    }
  },
  "$defs": {
    "OnTimeout": {
      "type": "string",
      "enum": [
        "throw",
        "continue",
        "compensate",
        "log"
      ]
    },
    "Sla": {
      "type": "object",
      "additionalProperties": false,
      "properties": {
        "timeoutMs": {
          "type": "number",
          "minimum": 0
        },
        "onTimeout": {
          "$ref": "#/$defs/OnTimeout"
        },
        "errorCode": {
          "type": "string"
        },
        "warningThresholdMs": {
          "type": "number",
          "minimum": 0
        },
        "p95LatencyMs": {
          "type": "number",
          "minimum": 0,
          "description": "P95 レイテンシ目標 (ms)。超過時は監視 alert 対象"
        }
      },
      "if": {
        "properties": {
          "onTimeout": {
            "enum": [
              "throw",
              "compensate"
            ]
          }
        },
        "required": [
          "onTimeout"
        ]
      },
      "then": {
        "required": [
          "errorCode"
        ]
      }
    },
    "TestScenario": {
      "type": "object",
      "required": [
        "id",
        "name",
        "given",
        "when",
        "then"
      ],
      "additionalProperties": false,
      "properties": {
        "id": {
          "$ref": "common.v2.schema.json#/$defs/LocalId"
        },
        "name": {
          "type": "string"
        },
        "description": {
          "$ref": "common.v2.schema.json#/$defs/Description"
        },
        "given": {
          "type": "array",
          "items": {
            "$ref": "#/$defs/TestPrecondition"
          }
        },
        "when": {
          "$ref": "#/$defs/TestInvocation"
        },
        "then": {
          "type": "array",
          "items": {
            "$ref": "#/$defs/TestAssertion"
          }
        },
        "tags": {
          "type": "array",
          "items": {
            "type": "string"
          }
        }
      }
    },
    "TestPrecondition": {
      "oneOf": [
        {
          "type": "object",
          "required": [
            "kind",
            "table",
            "rows"
          ],
          "additionalProperties": false,
          "properties": {
            "kind": {
              "const": "dbState"
            },
            "table": {
              "type": "string"
            },
            "rows": {
              "type": "array",
              "items": {
                "type": "object",
                "additionalProperties": true
              }
            }
          }
        },
        {
          "type": "object",
          "required": [
            "kind",
            "context"
          ],
          "additionalProperties": false,
          "properties": {
            "kind": {
              "const": "sessionContext"
            },
            "context": {
              "type": "object",
              "additionalProperties": true
            }
          }
        },
        {
          "type": "object",
          "required": [
            "kind",
            "externalRef",
            "responseMock"
          ],
          "additionalProperties": false,
          "properties": {
            "kind": {
              "const": "externalStub"
            },
            "externalRef": {
              "type": "string"
            },
            "responseMock": true
          }
        },
        {
          "type": "object",
          "required": [
            "kind",
            "now"
          ],
          "additionalProperties": false,
          "properties": {
            "kind": {
              "const": "clock"
            },
            "now": {
              "type": "string",
              "format": "date-time"
            }
          }
        }
      ]
    },
    "TestInvocation": {
      "type": "object",
      "required": [
        "actionId",
        "input"
      ],
      "additionalProperties": false,
      "properties": {
        "actionId": {
          "type": "string"
        },
        "input": {
          "type": "object",
          "additionalProperties": true
        }
      }
    },
    "TestAssertion": {
      "oneOf": [
        {
          "type": "object",
          "required": [
            "kind",
            "expected"
          ],
          "additionalProperties": false,
          "properties": {
            "kind": {
              "const": "outcome"
            },
            "expected": {
              "type": "string"
            }
          }
        },
        {
          "type": "object",
          "required": [
            "kind",
            "table",
            "match"
          ],
          "additionalProperties": false,
          "properties": {
            "kind": {
              "const": "dbRow"
            },
            "table": {
              "type": "string"
            },
            "match": {
              "type": "object",
              "additionalProperties": true
            },
            "count": {
              "type": "integer",
              "minimum": 0
            }
          }
        },
        {
          "type": "object",
          "required": [
            "kind",
            "path"
          ],
          "additionalProperties": false,
          "properties": {
            "kind": {
              "const": "output"
            },
            "path": {
              "type": "string"
            },
            "equals": true,
            "matches": {
              "type": "string",
              "format": "regex"
            }
          }
        },
        {
          "type": "object",
          "required": [
            "kind",
            "externalRef"
          ],
          "additionalProperties": false,
          "properties": {
            "kind": {
              "const": "externalCall"
            },
            "externalRef": {
              "type": "string"
            },
            "method": {
              "type": "string"
            },
            "bodyMatch": {
              "type": "object",
              "additionalProperties": true
            }
          }
        },
        {
          "type": "object",
          "required": [
            "kind",
            "action"
          ],
          "additionalProperties": false,
          "properties": {
            "kind": {
              "const": "auditLog"
            },
            "action": {
              "type": "string"
            },
            "result": {
              "$ref": "#/$defs/AuditResult"
            }
          }
        },
        {
          "type": "object",
          "required": [
            "kind",
            "msgKey"
          ],
          "additionalProperties": false,
          "properties": {
            "kind": {
              "const": "errorMessage"
            },
            "msgKey": {
              "type": "string"
            }
          }
        }
      ]
    },
    "ActionTrigger": {
      "type": "string",
      "enum": [
        "click",
        "submit",
        "select",
        "change",
        "load",
        "timer",
        "auto",
        "other"
      ]
    },
    "CacheHint": {
      "description": "キャッシュヒント (#423 B-4)。GET 系クエリのキャッシュ可否・TTL・無効化条件を宣言する",
      "type": "object",
      "required": [
        "ttlSeconds"
      ],
      "additionalProperties": false,
      "properties": {
        "ttlSeconds": {
          "type": "number",
          "minimum": 0,
          "description": "キャッシュ有効期間 (秒)"
        },
        "key": {
          "type": "string",
          "description": "キャッシュキー式。省略時はランタイムが自動生成"
        },
        "invalidateOn": {
          "type": "array",
          "items": {
            "type": "string"
          },
          "description": "このキャッシュを無効化するイベント名またはトピック名のリスト"
        },
        "note": {
          "type": "string",
          "description": "キャッシュ設定に関する補足説明。cross-flow 依存や運用上の注意事項を記述する"
        }
      }
    },
    "DataLineage": {
      "description": "データ系譜 (#423 B-2)。DbAccessStep がどのテーブルを読み書きするかを宣言的に記述する",
      "type": "object",
      "additionalProperties": false,
      "properties": {
        "reads": {
          "type": "array",
          "items": {
            "type": "string"
          },
          "description": "読み取るテーブル名の一覧"
        },
        "writes": {
          "type": "array",
          "items": {
            "type": "string"
          },
          "description": "書き込むテーブル名の一覧"
        }
      }
    },
    "EventDef": {
      "description": "イベント定義 (#423 B-1)。ProcessFlow.eventsCatalog の 1 エントリ",
      "type": "object",
      "additionalProperties": false,
      "properties": {
        "description": {
          "$ref": "common.v2.schema.json#/$defs/Description"
        },
        "payload": {
          "type": "object",
          "description": "ペイロードの JSON Schema (draft 2020-12)"
        }
      }
    },
    "GlossaryEntry": {
      "description": "ビジネス用語集の 1 エントリ (#423 B-3)",
      "type": "object",
      "required": [
        "definition"
      ],
      "additionalProperties": false,
      "properties": {
        "definition": {
          "type": "string",
          "description": "用語の定義"
        },
        "aliases": {
          "type": "array",
          "items": {
            "type": "string"
          },
          "description": "別名・略語のリスト"
        },
        "domainRef": {
          "type": "string",
          "description": "ドメインモデルやテーブル等への参照文字列"
        }
      }
    },
    "DecisionRecord": {
      "description": "ADR / 設計判断ログの 1 エントリ (#423 B-5)。MADR 形式を参考にした軽量 ADR",
      "type": "object",
      "required": [
        "id",
        "title",
        "status",
        "context",
        "decision"
      ],
      "additionalProperties": false,
      "properties": {
        "id": {
          "$ref": "common.v2.schema.json#/$defs/LocalId",
          "description": "例: ADR-001"
        },
        "title": {
          "type": "string"
        },
        "status": {
          "type": "string",
          "enum": [
            "proposed",
            "accepted",
            "deprecated",
            "superseded"
          ]
        },
        "context": {
          "type": "string",
          "description": "決定の背景・問題の説明"
        },
        "decision": {
          "type": "string",
          "description": "採択した決定内容"
        },
        "consequences": {
          "type": "string",
          "description": "結果・影響・トレードオフ"
        },
        "date": {
          "type": "string",
          "description": "ISO date (例: 2026-04-25)"
        }
      }
    },
    "EventPublishStep": {
      "allOf": [
        {
          "$ref": "#/$defs/StepBaseProps"
        },
        {
          "type": "object",
          "required": [
            "id",
            "kind",
            "description",
            "topic"
          ],
          "properties": {
            "topic": {
              "type": "string",
              "description": "パブリッシュ先のトピック名"
            },
            "eventRef": {
              "type": "string",
              "description": "ProcessFlow.eventsCatalog のキー参照"
            },
            "payload": {
              "type": "string",
              "description": "送信ペイロードの式 (例: '{ orderId: @orderId }')"
            },
            "kind": {
              "const": "eventPublish"
            }
          }
        }
      ],
      "unevaluatedProperties": false
    },
    "EventSubscribeStep": {
      "allOf": [
        {
          "$ref": "#/$defs/StepBaseProps"
        },
        {
          "type": "object",
          "required": [
            "id",
            "kind",
            "description",
            "topic"
          ],
          "properties": {
            "topic": {
              "type": "string",
              "description": "サブスクライブするトピック名"
            },
            "eventRef": {
              "type": "string",
              "description": "ProcessFlow.eventsCatalog のキー参照"
            },
            "filter": {
              "type": "string",
              "description": "受信フィルター条件の式 (例: '@event.type == \"OrderPlaced\"')"
            },
            "kind": {
              "const": "eventSubscribe"
            }
          }
        }
      ],
      "unevaluatedProperties": false
    },
    "HealthCheck": {
      "type": "object",
      "required": [
        "name",
        "type"
      ],
      "additionalProperties": false,
      "properties": {
        "name": {
          "type": "string"
        },
        "type": {
          "$ref": "#/$defs/HealthCheckKind"
        },
        "target": {
          "type": "string"
        },
        "timeout": {
          "type": "number",
          "minimum": 0
        }
      }
    },
    "HealthCheckGroup": {
      "type": "object",
      "required": [
        "checks"
      ],
      "additionalProperties": false,
      "properties": {
        "checks": {
          "type": "array",
          "items": {
            "$ref": "#/$defs/HealthCheck"
          }
        }
      }
    },
    "ReadinessCheckGroup": {
      "type": "object",
      "required": [
        "checks"
      ],
      "additionalProperties": false,
      "properties": {
        "checks": {
          "type": "array",
          "items": {
            "$ref": "#/$defs/HealthCheck"
          }
        },
        "minimumPassCount": {
          "type": "number",
          "minimum": 0
        }
      }
    },
    "ResourceQuota": {
      "type": "object",
      "additionalProperties": false,
      "properties": {
        "request": {
          "type": "string"
        },
        "limit": {
          "type": "string"
        }
      }
    },
    "ResourceRequirements": {
      "type": "object",
      "additionalProperties": false,
      "properties": {
        "cpu": {
          "$ref": "#/$defs/ResourceQuota"
        },
        "memory": {
          "$ref": "#/$defs/ResourceQuota"
        },
        "dbConnections": {
          "type": "number",
          "minimum": 0
        },
        "timeout": {
          "type": "number",
          "minimum": 0
        }
      }
    },
    "WorkflowPattern": {
      "type": "string",
      "enum": [
        "approval-sequential",
        "approval-parallel",
        "approval-veto",
        "approval-quorum",
        "approval-escalation",
        "review",
        "sign-off",
        "acknowledge",
        "branch-merge",
        "discussion",
        "ad-hoc"
      ]
    },
    "HttpMethod": {
      "type": "string",
      "enum": [
        "GET",
        "POST",
        "PUT",
        "PATCH",
        "DELETE"
      ]
    },
    "HttpAuthRequirement": {
      "type": "string",
      "enum": [
        "required",
        "optional",
        "none"
      ],
      "description": "認証要件。未指定は required 相当"
    },
    "HttpRoute": {
      "type": "object",
      "required": [
        "method",
        "path"
      ],
      "additionalProperties": false,
      "properties": {
        "method": {
          "$ref": "#/$defs/HttpMethod"
        },
        "path": {
          "type": "string"
        },
        "auth": {
          "$ref": "#/$defs/HttpAuthRequirement"
        }
      }
    },
    "Marker": {
      "description": "1 マーカー (#261)。人間→AI または AI→人間の 1 メッセージ相当",
      "type": "object",
      "required": [
        "id",
        "kind",
        "body",
        "author",
        "createdAt"
      ],
      "additionalProperties": false,
      "properties": {
        "id": {
          "$ref": "common.v2.schema.json#/$defs/Uuid"
        },
        "kind": {
          "$ref": "#/$defs/MarkerKind"
        },
        "body": {
          "type": "string"
        },
        "stepId": {
          "type": "string"
        },
        "fieldPath": {
          "type": "string"
        },
        "author": {
          "$ref": "#/$defs/MarkerAuthor"
        },
        "createdAt": {
          "$ref": "common.v2.schema.json#/$defs/Timestamp"
        },
        "resolvedAt": {
          "$ref": "common.v2.schema.json#/$defs/Timestamp"
        },
        "resolution": {
          "type": "string"
        },
        "code": {
          "type": "string",
          "description": "警告由来 marker の validator code (UNKNOWN_IDENTIFIER 等)"
        },
        "path": {
          "type": "string",
          "description": "警告由来 marker の JSON path"
        },
        "shape": {
          "$ref": "#/$defs/MarkerShape"
        }
      }
    },
    "MarkerShape": {
      "description": "自由描画マーカーの形状 (#261)。SVG viewBox=0 0 100 100 の相対座標。anchorStepId 指定時はその DOM 要素 bbox 相対",
      "type": "object",
      "required": [
        "type",
        "d"
      ],
      "additionalProperties": false,
      "properties": {
        "type": {
          "type": "string",
          "enum": [
            "path"
          ]
        },
        "d": {
          "type": "string",
          "description": "SVG path の d 属性 (0-100 の % 座標)"
        },
        "color": {
          "type": "string",
          "description": "描画色 (#ef4444 既定)"
        },
        "strokeWidth": {
          "type": "number",
          "minimum": 0.1
        },
        "anchorStepId": {
          "type": "string",
          "description": "DOM anchor: 描画を特定 step に紐付け (座標はこの step の bbox 相対 %)"
        },
        "anchorFieldPath": {
          "type": "string",
          "description": "DOM anchor 内の field 細分 (例: sql / conditions / expression)"
        }
      }
    },
    "SecretRef": {
      "description": "Secrets カタログの 1 エントリ (#261 v1.6 / #414 で values 拡張)。値は含まない。values は環境別の参照式 (vault://... / env://... / k8s-secret://...) を入れる規約",
      "type": "object",
      "required": [
        "source",
        "name"
      ],
      "additionalProperties": false,
      "properties": {
        "source": {
          "type": "string",
          "enum": [
            "env",
            "vault",
            "file"
          ]
        },
        "name": {
          "type": "string"
        },
        "description": {
          "$ref": "common.v2.schema.json#/$defs/Description"
        },
        "rotationDays": {
          "type": "integer",
          "minimum": 1
        },
        "lastRotatedAt": {
          "type": "string",
          "format": "date-time"
        },
        "values": {
          "type": "object",
          "description": "環境別の参照式 (#414)。dev / staging / prod 等の任意キー。実値ではなく vault://path / env://NAME / k8s-secret://name 形式の参照を入れる",
          "additionalProperties": {
            "type": "string"
          }
        }
      }
    },
    "EnvVarEntry": {
      "description": "環境変数カタログの 1 エントリ (#414)。Power Platform Environment Variables 由来。型 + 環境別 values + default を宣言する。@env.<KEY> で式から参照される",
      "type": "object",
      "required": [
        "type"
      ],
      "additionalProperties": false,
      "properties": {
        "type": {
          "type": "string",
          "enum": [
            "string",
            "number",
            "boolean"
          ],
          "description": "値の型。実装側はこの型に従って parse する"
        },
        "description": {
          "$ref": "common.v2.schema.json#/$defs/Description"
        },
        "values": {
          "type": "object",
          "description": "環境別の値。dev / staging / prod 等の任意キー。値は type と整合した primitive (string / number / boolean) または式文字列",
          "additionalProperties": true
        },
        "default": {
          "description": "values で当該環境キーが未指定時に使う既定値。type と整合した primitive を入れる"
        }
      }
    },
    "ErrorCatalogEntry": {
      "type": "object",
      "additionalProperties": false,
      "properties": {
        "httpStatus": {
          "type": "integer",
          "minimum": 100,
          "maximum": 599
        },
        "defaultMessage": {
          "type": "string"
        },
        "responseRef": {
          "type": "string"
        },
        "description": {
          "$ref": "common.v2.schema.json#/$defs/Description"
        }
      }
    },
    "DomainDef": {
      "description": "Domain カタログの 1 エントリ (#422 P2-1 / GeneXus 由来)。型・制約・UI ヒントを宣言し、StructuredField.domainRef から参照される",
      "type": "object",
      "required": [
        "type"
      ],
      "additionalProperties": false,
      "properties": {
        "type": {
          "$ref": "#/$defs/FieldType"
        },
        "constraints": {
          "type": "array",
          "items": {
            "$ref": "#/$defs/ValidationRule"
          },
          "description": "このドメインに適用する ValidationRule 一覧"
        },
        "uiHint": {
          "type": "string",
          "description": "UI 表示ヒント (例: \"email\", \"tel\", \"textarea\"). HTML input type 相当"
        },
        "description": {
          "$ref": "common.v2.schema.json#/$defs/Description"
        }
      }
    },
    "FunctionDef": {
      "description": "組み込み関数カタログの 1 エントリ (#422 P2-5 / Wagby 由来)。@fn.<name> 参照形式で式から呼び出される",
      "type": "object",
      "required": [
        "signature",
        "returnType",
        "description"
      ],
      "additionalProperties": false,
      "properties": {
        "signature": {
          "type": "string",
          "description": "関数シグネチャ (例: \"formatCurrency(amount: number, currency: string): string\")"
        },
        "returnType": {
          "type": "string",
          "description": "戻り値の型 (例: \"string\", \"number\", \"boolean\")"
        },
        "description": {
          "$ref": "common.v2.schema.json#/$defs/Description"
        },
        "examples": {
          "type": "array",
          "items": {
            "type": "string"
          },
          "description": "使用例 (例: [\"@fn.formatCurrency(@subtotal, 'JPY') // => \\\"¥1,000\\\"\"])"
        }
      }
    },
    "BodySchemaRef": {
      "oneOf": [
        {
          "type": "object",
          "required": [
            "typeRef"
          ],
          "additionalProperties": false,
          "properties": {
            "typeRef": {
              "type": "string",
              "description": "型カタログへの名前参照 (例: \"CustomerResponse\")"
            }
          }
        },
        {
          "type": "object",
          "required": [
            "schema"
          ],
          "additionalProperties": false,
          "properties": {
            "schema": {
              "type": "object",
              "description": "インライン JSON Schema"
            }
          }
        }
      ]
    },
    "HttpResponseSpec": {
      "type": "object",
      "required": [
        "status"
      ],
      "additionalProperties": false,
      "properties": {
        "id": {
          "$ref": "common.v2.schema.json#/$defs/LocalId"
        },
        "status": {
          "type": "integer",
          "minimum": 100,
          "maximum": 599
        },
        "contentType": {
          "type": "string"
        },
        "bodySchema": {
          "$ref": "#/$defs/BodySchemaRef"
        },
        "description": {
          "$ref": "common.v2.schema.json#/$defs/Description"
        },
        "when": {
          "type": "string"
        }
      }
    },
    "FieldType": {
      "oneOf": [
        {
          "type": "string",
          "enum": [
            "string",
            "number",
            "boolean",
            "date",
            "object[]",
            "string[]",
            "number[]"
          ]
        },
        {
          "description": "配列型。itemType で要素型を再帰的に表現。例: Array<{itemId, quantity}>",
          "type": "object",
          "required": [
            "kind",
            "itemType"
          ],
          "additionalProperties": false,
          "properties": {
            "kind": {
              "const": "array"
            },
            "itemType": {
              "$ref": "#/$defs/FieldType"
            }
          }
        },
        {
          "description": "オブジェクト型。fields[] で構造を表現。custom の label 逃げを置き換える",
          "type": "object",
          "required": [
            "kind",
            "fields"
          ],
          "additionalProperties": false,
          "properties": {
            "kind": {
              "const": "object"
            },
            "fields": {
              "type": "array",
              "items": {
                "$ref": "#/$defs/StructuredField"
              }
            }
          }
        },
        {
          "type": "object",
          "required": [
            "kind",
            "tableId"
          ],
          "additionalProperties": false,
          "properties": {
            "kind": {
              "const": "tableRow"
            },
            "tableId": {
              "type": "string"
            }
          }
        },
        {
          "type": "object",
          "required": [
            "kind",
            "tableId"
          ],
          "additionalProperties": false,
          "properties": {
            "kind": {
              "const": "tableList"
            },
            "tableId": {
              "type": "string"
            }
          }
        },
        {
          "type": "object",
          "required": [
            "kind",
            "screenId"
          ],
          "additionalProperties": false,
          "properties": {
            "kind": {
              "const": "screenInput"
            },
            "screenId": {
              "$ref": "common.v2.schema.json#/$defs/Uuid"
            }
          }
        },
        {
          "description": "ファイル型。バッチ処理の入出力ファイル等。format で CSV/ZIP 等の形式を表現。",
          "type": "object",
          "required": [
            "kind"
          ],
          "additionalProperties": false,
          "properties": {
            "kind": {
              "const": "file"
            },
            "format": {
              "type": "string",
              "description": "ファイル形式 (例: csv, tsv, zip, pdf)"
            }
          }
        }
      ]
    },
    "StructuredField": {
      "type": "object",
      "required": [
        "name",
        "type"
      ],
      "additionalProperties": false,
      "properties": {
        "name": {
          "type": "string"
        },
        "label": {
          "type": "string"
        },
        "type": {
          "$ref": "#/$defs/FieldType"
        },
        "required": {
          "type": "boolean"
        },
        "description": {
          "$ref": "common.v2.schema.json#/$defs/Description"
        },
        "format": {
          "type": "string",
          "description": "採番形式・フォーマットパターン。文字列型フィールドで @conv.numbering.* 参照や正規表現パターンを構造化宣言する (#253)"
        },
        "defaultValue": {
          "type": "string"
        },
        "screenItemRef": {
          "type": "object",
          "required": [
            "screenId",
            "itemId"
          ],
          "additionalProperties": false,
          "description": "画面項目定義への参照 (#321)。設定時は ScreenItem から name/label/type/required/pattern/maxLength 等を上書き解釈する",
          "properties": {
            "screenId": {
              "$ref": "common.v2.schema.json#/$defs/Uuid"
            },
            "itemId": {
              "type": "string"
            }
          }
        },
        "domainRef": {
          "type": "string",
          "description": "Domain カタログへの参照 (#422 P2-1 / D-2)。ProcessFlow.domainsCatalog のキー (例: \"EmailAddress\")。型・制約・uiHint を domainsCatalog 側から継承する"
        },
        "formula": {
          "type": "string",
          "description": "属性レベル計算式 (#422 P2-2 / GeneXus 由来)。= で始まる式文字列 (例: \"= a + b\")。ScreenItem の computed と対になる概念"
        }
      }
    },
    "ActionFields": {
      "type": "array",
      "items": {
        "$ref": "#/$defs/StructuredField"
      }
    },
    "ActionDefinition": {
      "type": "object",
      "required": [
        "id",
        "name",
        "trigger",
        "steps"
      ],
      "additionalProperties": false,
      "properties": {
        "id": {
          "$ref": "common.v2.schema.json#/$defs/LocalId"
        },
        "name": {
          "type": "string"
        },
        "trigger": {
          "$ref": "#/$defs/ActionTrigger"
        },
        "elementRef": {
          "type": "string"
        },
        "description": {
          "$ref": "common.v2.schema.json#/$defs/Description"
        },
        "inputs": {
          "$ref": "#/$defs/ActionFields"
        },
        "outputs": {
          "$ref": "#/$defs/ActionFields"
        },
        "maturity": {
          "$ref": "common.v2.schema.json#/$defs/MaturityLevel"
        },
        "sla": {
          "$ref": "#/$defs/Sla"
        },
        "requiredPermissions": {
          "type": "array",
          "items": {
            "type": "string"
          }
        },
        "httpRoute": {
          "$ref": "#/$defs/HttpRoute"
        },
        "responses": {
          "type": "array",
          "items": {
            "$ref": "#/$defs/HttpResponseSpec"
          }
        },
        "steps": {
          "type": "array",
          "items": {
            "$ref": "#/$defs/Step"
          }
        }
      }
    },
    "StepNoteType": {
      "type": "string",
      "enum": [
        "assumption",
        "prerequisite",
        "todo",
        "deferred",
        "question"
      ]
    },
    "StepNote": {
      "type": "object",
      "required": [
        "id",
        "type",
        "body",
        "createdAt"
      ],
      "additionalProperties": false,
      "properties": {
        "id": {
          "$ref": "common.v2.schema.json#/$defs/LocalId"
        },
        "type": {
          "$ref": "#/$defs/StepNoteType"
        },
        "body": {
          "type": "string"
        },
        "createdAt": {
          "$ref": "common.v2.schema.json#/$defs/Timestamp"
        }
      }
    },
    "OutputBindingOperation": {
      "type": "string",
      "enum": [
        "assign",
        "accumulate",
        "push"
      ]
    },
    "OutputBindingObject": {
      "type": "object",
      "required": [
        "name"
      ],
      "additionalProperties": false,
      "properties": {
        "name": {
          "type": "string"
        },
        "operation": {
          "$ref": "#/$defs/OutputBindingOperation"
        },
        "initialValue": {
          "description": "初期値。JSON 値 (例: [], 0) または式文字列 (例: '[]', '@emptyArr') (#253)。accumulate: 数値 (既定 0)、push: 配列 (既定 [])"
        }
      }
    },
    "OutputBinding": {
      "$ref": "#/$defs/OutputBindingObject"
    },
    "TxBoundaryRole": {
      "type": "string",
      "enum": [
        "begin",
        "member",
        "end"
      ]
    },
    "TxBoundary": {
      "type": "object",
      "required": [
        "role",
        "txId"
      ],
      "additionalProperties": false,
      "properties": {
        "role": {
          "$ref": "#/$defs/TxBoundaryRole"
        },
        "txId": {
          "type": "string"
        }
      }
    },
    "ExternalChainPhase": {
      "type": "string",
      "enum": [
        "authorize",
        "capture",
        "cancel",
        "other"
      ]
    },
    "ExternalChain": {
      "type": "object",
      "required": [
        "chainId",
        "phase"
      ],
      "additionalProperties": false,
      "properties": {
        "chainId": {
          "type": "string"
        },
        "phase": {
          "$ref": "#/$defs/ExternalChainPhase"
        }
      }
    },
    "StepBaseProps": {
      "description": "全ステップ共通フィールド (StepBase のプロパティ集合)。各 Step variant はこれを allOf でマージする",
      "type": "object",
      "properties": {
        "id": {
          "$ref": "common.v2.schema.json#/$defs/LocalId"
        },
        "description": {
          "$ref": "common.v2.schema.json#/$defs/Description"
        },
        "note": {
          "type": "string"
        },
        "notes": {
          "type": "array",
          "items": {
            "$ref": "#/$defs/StepNote"
          }
        },
        "maturity": {
          "$ref": "common.v2.schema.json#/$defs/MaturityLevel"
        },
        "sla": {
          "$ref": "#/$defs/Sla"
        },
        "runIf": {
          "$ref": "common.v2.schema.json#/$defs/ExpressionString"
        },
        "requiredPermissions": {
          "type": "array",
          "items": {
            "type": "string"
          }
        },
        "outputBinding": {
          "$ref": "#/$defs/OutputBinding"
        },
        "txBoundary": {
          "$ref": "#/$defs/TxBoundary"
        },
        "transactional": {
          "type": "boolean"
        },
        "compensatesFor": {
          "type": "string"
        },
        "externalChain": {
          "$ref": "#/$defs/ExternalChain"
        },
        "subSteps": {
          "type": "array",
          "items": {
            "$ref": "#/$defs/Step"
          }
        }
      }
    },
    "ValidationRuleType": {
      "type": "string",
      "enum": [
        "required",
        "regex",
        "maxLength",
        "minLength",
        "range",
        "enum",
        "custom"
      ]
    },
    "ValidationRuleKind": {
      "type": "string",
      "enum": [
        "error",
        "msg",
        "noaccept",
        "default"
      ]
    },
    "ValidationRule": {
      "type": "object",
      "required": [
        "field",
        "type"
      ],
      "additionalProperties": false,
      "properties": {
        "field": {
          "type": "string"
        },
        "type": {
          "$ref": "#/$defs/ValidationRuleType"
        },
        "kind": {
          "$ref": "#/$defs/ValidationRuleKind",
          "description": "GeneXus 由来の動作種別 (#422 P2-3)。type とは別概念。省略時はランタイム既定 (通常 Error 相当)"
        },
        "pattern": {
          "type": "string"
        },
        "patternRef": {
          "type": "string",
          "description": "type=regex 時のパターンを @conv.regex.* 参照で指定するバリアント (リテラル pattern の代替)。例: '@conv.regex.product-code'"
        },
        "length": {
          "type": "integer",
          "minimum": 0
        },
        "min": {
          "type": "number"
        },
        "max": {
          "type": "number"
        },
        "minRef": {
          "type": "string",
          "description": "type=range 時の最小値を @conv.limit.* 参照で指定するバリアント (数値リテラルの代替) (#253)"
        },
        "maxRef": {
          "type": "string",
          "description": "type=range 時の最大値を @conv.limit.* 参照で指定するバリアント (数値リテラルの代替) (#253)"
        },
        "values": {
          "type": "array",
          "items": {
            "type": "string"
          }
        },
        "condition": {
          "type": "string"
        },
        "message": {
          "type": "string"
        }
      }
    },
    "ValidationInlineBranch": {
      "type": "object",
      "required": [
        "ok",
        "ng"
      ],
      "additionalProperties": false,
      "properties": {
        "ok": {
          "type": "array",
          "items": {
            "$ref": "#/$defs/Step"
          }
        },
        "ng": {
          "type": "array",
          "items": {
            "$ref": "#/$defs/Step"
          }
        },
        "ngJumpTo": {
          "type": "string"
        },
        "ngResponseRef": {
          "type": "string"
        },
        "ngBodyExpression": {
          "$ref": "common.v2.schema.json#/$defs/ExpressionString"
        },
        "ngEventPublish": {
          "type": "object",
          "description": "ng 時に eventPublish を実行してから ngResponseRef を返す。",
          "required": [
            "topic",
            "eventRef",
            "payload"
          ],
          "additionalProperties": false,
          "properties": {
            "topic": {
              "type": "string"
            },
            "eventRef": {
              "type": "string"
            },
            "payload": {
              "type": "string"
            }
          }
        }
      }
    },
    "ValidationStep": {
      "allOf": [
        {
          "$ref": "#/$defs/StepBaseProps"
        },
        {
          "type": "object",
          "required": [
            "id",
            "kind",
            "description",
            "conditions"
          ],
          "properties": {
            "conditions": {
              "type": "string"
            },
            "rules": {
              "type": "array",
              "items": {
                "$ref": "#/$defs/ValidationRule"
              }
            },
            "fieldErrorsVar": {
              "type": "string",
              "description": "rules[] の評価結果変数名 (#261 v1.4)。既定 \"fieldErrors\""
            },
            "inlineBranch": {
              "$ref": "#/$defs/ValidationInlineBranch"
            },
            "kind": {
              "const": "validation"
            }
          }
        }
      ],
      "unevaluatedProperties": false
    },
    "DbOperation": {
      "type": "string",
      "enum": [
        "SELECT",
        "INSERT",
        "UPDATE",
        "DELETE",
        "MERGE",
        "LOCK"
      ]
    },
    "AffectedRowsOperator": {
      "type": "string",
      "enum": [
        ">",
        ">=",
        "=",
        "<",
        "<="
      ]
    },
    "AffectedRowsCheck": {
      "type": "object",
      "required": [
        "operator",
        "expected",
        "onViolation"
      ],
      "additionalProperties": false,
      "properties": {
        "operator": {
          "$ref": "#/$defs/AffectedRowsOperator"
        },
        "expected": {
          "type": "integer"
        },
        "onViolation": {
          "type": "string",
          "enum": [
            "throw",
            "abort",
            "log",
            "continue"
          ]
        },
        "errorCode": {
          "type": "string"
        },
        "description": {
          "$ref": "common.v2.schema.json#/$defs/Description"
        }
      }
    },
    "DbAccessStep": {
      "allOf": [
        {
          "$ref": "#/$defs/StepBaseProps"
        },
        {
          "type": "object",
          "required": [
            "id",
            "kind",
            "description",
            "tableName",
            "operation"
          ],
          "properties": {
            "tableName": {
              "type": "string"
            },
            "tableId": {
              "type": "string"
            },
            "operation": {
              "$ref": "#/$defs/DbOperation"
            },
            "fields": {
              "type": "string"
            },
            "sql": {
              "type": "string"
            },
            "bulkValues": {
              "type": "string",
              "description": "一括 INSERT 時に VALUES 句へ展開する配列変数の参照 (例: \"@poItemValues\")。配列の各要素がレコードとして INSERT される (#253)"
            },
            "affectedRowsCheck": {
              "$ref": "#/$defs/AffectedRowsCheck"
            },
            "lineage": {
              "$ref": "#/$defs/DataLineage",
              "description": "データ系譜 (#423 B-2)。このステップが読み書きするテーブルを宣言する"
            },
            "cache": {
              "$ref": "#/$defs/CacheHint",
              "description": "キャッシュヒント (#423 B-4)。SELECT 系クエリのキャッシュ設定"
            },
            "kind": {
              "const": "dbAccess"
            }
          }
        }
      ],
      "unevaluatedProperties": false
    },
    "ExternalCallOutcome": {
      "type": "string",
      "enum": [
        "success",
        "failure",
        "timeout"
      ]
    },
    "ExternalCallOutcomeSpec": {
      "type": "object",
      "required": [
        "action"
      ],
      "additionalProperties": false,
      "properties": {
        "action": {
          "type": "string",
          "enum": [
            "continue",
            "abort",
            "compensate"
          ]
        },
        "description": {
          "$ref": "common.v2.schema.json#/$defs/Description"
        },
        "jumpTo": {
          "type": "string"
        },
        "sideEffects": {
          "description": "副作用ステップ列 (#261): ReturnStep は禁止。action=abort との意味衝突を避けるため。レスポンス返却は ReturnStep として通常のフロー上に配置する",
          "type": "array",
          "items": {
            "$ref": "#/$defs/NonReturnStep"
          }
        },
        "sameAs": {
          "$ref": "#/$defs/ExternalCallOutcome"
        }
      }
    },
    "CriterionType": {
      "description": "Criterion の評価種別 (#427 P3-2 / Arazzo 由来)",
      "type": "string",
      "enum": [
        "simple",
        "regex",
        "jsonpath",
        "xpath"
      ]
    },
    "StructuredCriterion": {
      "description": "型付き条件式 (#427 P3-2)。Arazzo 1.0 の successCriteria 互換",
      "type": "object",
      "required": [
        "type",
        "expression"
      ],
      "additionalProperties": false,
      "properties": {
        "type": {
          "$ref": "#/$defs/CriterionType"
        },
        "expression": {
          "$ref": "common.v2.schema.json#/$defs/ExpressionString",
          "description": "評価式。Arazzo Runtime Expression ($記法) 推奨。simple: \"$statusCode == 200\", regex: \"^pi_\", jsonpath: \"$.status\", xpath: \"//result/text()\". 旧 @記法 (@statusCode 等) は後方互換として引き続き有効"
        },
        "context": {
          "type": "string",
          "description": "jsonpath / xpath の評価対象 (JSON / XML オブジェクト)。Arazzo Runtime Expression ($記法) 推奨: \"$response.body\", \"$response.body#/id\". 旧 @記法 (@responseBody 等) は後方互換として引き続き有効"
        }
      }
    },
    "Criterion": {
      "$ref": "#/$defs/StructuredCriterion"
    },
    "NonReturnStep": {
      "description": "sideEffects 配列で使える Step の制限サブセット。ReturnStep を除外 (#261)",
      "oneOf": [
        {
          "$ref": "#/$defs/ValidationStep"
        },
        {
          "$ref": "#/$defs/DbAccessStep"
        },
        {
          "$ref": "#/$defs/ExternalSystemStep"
        },
        {
          "$ref": "#/$defs/CommonProcessStep"
        },
        {
          "$ref": "#/$defs/ScreenTransitionStep"
        },
        {
          "$ref": "#/$defs/DisplayUpdateStep"
        },
        {
          "$ref": "#/$defs/BranchStep"
        },
        {
          "$ref": "#/$defs/LoopStep"
        },
        {
          "$ref": "#/$defs/LoopBreakStep"
        },
        {
          "$ref": "#/$defs/LoopContinueStep"
        },
        {
          "$ref": "#/$defs/JumpStep"
        },
        {
          "$ref": "#/$defs/ComputeStep"
        },
        {
          "$ref": "#/$defs/LogStep"
        },
        {
          "$ref": "#/$defs/AuditStep"
        },
        {
          "$ref": "#/$defs/WorkflowStep"
        },
        {
          "$ref": "#/$defs/TransactionScopeStep"
        },
        {
          "$ref": "#/$defs/EventPublishStep"
        },
        {
          "$ref": "#/$defs/EventSubscribeStep"
        },
        {
          "$ref": "#/$defs/ClosingStep"
        },
        {
          "$ref": "#/$defs/CdcStep"
        },
        {
          "$ref": "#/$defs/OtherStep"
        }
      ]
    },
    "RetryPolicy": {
      "type": "object",
      "required": [
        "maxAttempts"
      ],
      "additionalProperties": false,
      "properties": {
        "maxAttempts": {
          "type": "integer",
          "minimum": 1
        },
        "backoff": {
          "type": "string",
          "enum": [
            "fixed",
            "exponential"
          ]
        },
        "initialDelayMs": {
          "type": "integer",
          "minimum": 0
        }
      }
    },
    "CircuitBreakerConfig": {
      "type": "object",
      "required": [
        "failureThreshold",
        "timeout"
      ],
      "additionalProperties": false,
      "properties": {
        "failureThreshold": {
          "type": "number",
          "minimum": 0
        },
        "timeout": {
          "type": "number",
          "minimum": 0
        },
        "halfOpenMaxCalls": {
          "type": "number",
          "minimum": 0
        }
      }
    },
    "BulkheadConfig": {
      "type": "object",
      "required": [
        "maxConcurrent"
      ],
      "additionalProperties": false,
      "properties": {
        "maxConcurrent": {
          "type": "number",
          "minimum": 0
        },
        "maxWait": {
          "type": "number",
          "minimum": 0
        }
      }
    },
    "ExternalAuthKind": {
      "type": "string",
      "enum": [
        "bearer",
        "basic",
        "apiKey",
        "oauth2",
        "none"
      ]
    },
    "ExternalAuth": {
      "type": "object",
      "required": [
        "kind"
      ],
      "additionalProperties": false,
      "properties": {
        "kind": {
          "$ref": "#/$defs/ExternalAuthKind"
        },
        "tokenRef": {
          "type": "string",
          "description": "秘密値の参照文字列 (例: \"ENV:STRIPE_SECRET_KEY\", \"SECRET:stripe/api-key\")"
        },
        "headerName": {
          "type": "string"
        }
      }
    },
    "ExternalHttpCall": {
      "description": "外部 HTTP 呼出の構造化 (#261 v1.3)。path は式補間可",
      "type": "object",
      "required": [
        "method",
        "path"
      ],
      "additionalProperties": false,
      "properties": {
        "method": {
          "$ref": "#/$defs/HttpMethod"
        },
        "path": {
          "type": "string"
        },
        "query": {
          "type": "object",
          "additionalProperties": {
            "type": "string"
          }
        },
        "body": {
          "type": "string"
        }
      }
    },
    "ExternalSystemCatalogEntry": {
      "description": "外部システムカタログの 1 エントリ (#261 v1.3)",
      "type": "object",
      "required": [
        "name"
      ],
      "additionalProperties": false,
      "properties": {
        "name": {
          "type": "string"
        },
        "baseUrl": {
          "type": "string"
        },
        "openApiSpec": {
          "type": "string",
          "description": "OpenAPI specification URL or relative path (#413)"
        },
        "auth": {
          "$ref": "#/$defs/ExternalAuth"
        },
        "timeoutMs": {
          "type": "integer",
          "minimum": 0
        },
        "retryPolicy": {
          "$ref": "#/$defs/RetryPolicy"
        },
        "headers": {
          "type": "object",
          "additionalProperties": {
            "type": "string"
          }
        },
        "description": {
          "$ref": "common.v2.schema.json#/$defs/Description"
        },
        "responseSchema": {
          "type": "object",
          "description": "外部システム API のレスポンス JSON スキーマ (参考定義)。required / properties を記述する。",
          "additionalProperties": true
        }
      }
    },
    "ExternalSystemStep": {
      "allOf": [
        {
          "$ref": "#/$defs/StepBaseProps"
        },
        {
          "type": "object",
          "required": [
            "id",
            "kind",
            "description",
            "systemName"
          ],
          "properties": {
            "systemName": {
              "type": "string"
            },
            "systemRef": {
              "type": "string",
              "description": "ProcessFlow.externalSystemCatalog のキー参照 (#261 v1.3)"
            },
            "httpCall": {
              "$ref": "#/$defs/ExternalHttpCall"
            },
            "operationRef": {
              "type": "string",
              "description": "OpenAPI operation reference. When httpCall is also present, operationRef takes precedence (#413)."
            },
            "operationId": {
              "type": "string",
              "description": "OpenAPI operationId (#413)"
            },
            "requestBodyRef": {
              "type": "string",
              "description": "JSON Pointer / $ref to request body schema (#413)"
            },
            "responseRef": {
              "type": "string",
              "description": "JSON Pointer / $ref to response schema (#413)"
            },
            "outcomes": {
              "type": "object",
              "additionalProperties": false,
              "properties": {
                "success": {
                  "$ref": "#/$defs/ExternalCallOutcomeSpec"
                },
                "failure": {
                  "$ref": "#/$defs/ExternalCallOutcomeSpec"
                },
                "timeout": {
                  "$ref": "#/$defs/ExternalCallOutcomeSpec"
                }
              }
            },
            "timeoutMs": {
              "type": "integer",
              "minimum": 0
            },
            "retryPolicy": {
              "$ref": "#/$defs/RetryPolicy"
            },
            "circuitBreaker": {
              "$ref": "#/$defs/CircuitBreakerConfig"
            },
            "bulkhead": {
              "$ref": "#/$defs/BulkheadConfig"
            },
            "fireAndForget": {
              "type": "boolean"
            },
            "auth": {
              "$ref": "#/$defs/ExternalAuth"
            },
            "idempotencyKey": {
              "type": "string"
            },
            "headers": {
              "type": "object",
              "additionalProperties": {
                "type": "string"
              }
            },
            "apiVersion": {
              "type": "string",
              "description": "API バージョン override (#423 B-6)。ProcessFlow.apiVersion より優先"
            },
            "cache": {
              "$ref": "#/$defs/CacheHint",
              "description": "キャッシュヒント (#423 B-4)。GET 系 API レスポンスのキャッシュ設定"
            },
            "successCriteria": {
              "type": "array",
              "items": {
                "$ref": "#/$defs/Criterion"
              },
              "description": "Arazzo 互換の成功判定条件 (#427 P3-2)。Arazzo Export で successCriteria フィールドにマッピングされる"
            },
            "kind": {
              "const": "externalSystem"
            }
          }
        }
      ],
      "unevaluatedProperties": false
    },
    "CommonProcessStep": {
      "allOf": [
        {
          "$ref": "#/$defs/StepBaseProps"
        },
        {
          "type": "object",
          "required": [
            "id",
            "kind",
            "description",
            "refId"
          ],
          "properties": {
            "refId": {
              "type": "string"
            },
            "refName": {
              "type": "string"
            },
            "argumentMapping": {
              "type": "object",
              "additionalProperties": {
                "type": "string"
              }
            },
            "returnMapping": {
              "description": "呼び先フローの戻り値名 → 説明のマッピング (例: {\"処理結果\": \"0:正常終了, 1:異常終了\"})",
              "type": "object",
              "additionalProperties": {
                "type": "string"
              }
            },
            "kind": {
              "const": "commonProcess"
            }
          }
        }
      ],
      "unevaluatedProperties": false
    },
    "ScreenTransitionStep": {
      "allOf": [
        {
          "$ref": "#/$defs/StepBaseProps"
        },
        {
          "type": "object",
          "required": [
            "id",
            "kind",
            "description",
            "targetScreenName"
          ],
          "properties": {
            "targetScreenId": {
              "type": "string"
            },
            "targetScreenName": {
              "type": "string"
            },
            "kind": {
              "const": "screenTransition"
            }
          }
        }
      ],
      "unevaluatedProperties": false
    },
    "DisplayUpdateStep": {
      "allOf": [
        {
          "$ref": "#/$defs/StepBaseProps"
        },
        {
          "type": "object",
          "required": [
            "id",
            "kind",
            "description",
            "target"
          ],
          "properties": {
            "target": {
              "type": "string"
            },
            "kind": {
              "const": "displayUpdate"
            }
          }
        }
      ],
      "unevaluatedProperties": false
    },
    "BranchConditionVariant": {
      "description": "分岐条件の型付き variant (#176 / #261 v1.3)",
      "oneOf": [
        {
          "description": "tryCatch: errorCode 付きエラーを捕捉",
          "type": "object",
          "required": [
            "kind",
            "errorCode"
          ],
          "additionalProperties": false,
          "properties": {
            "kind": {
              "const": "tryCatch"
            },
            "errorCode": {
              "type": "string"
            },
            "description": {
              "$ref": "common.v2.schema.json#/$defs/Description"
            }
          }
        },
        {
          "description": "affectedRowsZero: 直前の DbAccess の rowCount が期待未満 (#261 v1.3)",
          "type": "object",
          "required": [
            "kind"
          ],
          "additionalProperties": false,
          "properties": {
            "kind": {
              "const": "affectedRowsZero"
            },
            "stepRef": {
              "type": "string"
            },
            "description": {
              "$ref": "common.v2.schema.json#/$defs/Description"
            }
          }
        },
        {
          "description": "externalOutcome: 直前の ExternalSystem の outcome 分岐 (#261 v1.3)",
          "type": "object",
          "required": [
            "kind",
            "outcome"
          ],
          "additionalProperties": false,
          "properties": {
            "kind": {
              "const": "externalOutcome"
            },
            "stepRef": {
              "type": "string"
            },
            "outcome": {
              "$ref": "#/$defs/ExternalCallOutcome"
            },
            "description": {
              "$ref": "common.v2.schema.json#/$defs/Description"
            }
          }
        }
      ]
    },
    "BranchCondition": {
      "$ref": "#/$defs/BranchConditionVariant"
    },
    "Branch": {
      "type": "object",
      "required": [
        "id",
        "code",
        "condition",
        "steps"
      ],
      "additionalProperties": false,
      "properties": {
        "id": {
          "$ref": "common.v2.schema.json#/$defs/LocalId"
        },
        "code": {
          "type": "string"
        },
        "label": {
          "type": "string"
        },
        "condition": {
          "$ref": "#/$defs/BranchCondition"
        },
        "steps": {
          "type": "array",
          "items": {
            "$ref": "#/$defs/Step"
          }
        }
      }
    },
    "ElseBranch": {
      "description": "else 分岐。condition は不要 (旧データ互換で optional として残す)",
      "type": "object",
      "required": [
        "id",
        "code",
        "steps"
      ],
      "additionalProperties": false,
      "properties": {
        "id": {
          "$ref": "common.v2.schema.json#/$defs/LocalId"
        },
        "code": {
          "type": "string"
        },
        "label": {
          "type": "string"
        },
        "description": {
          "$ref": "common.v2.schema.json#/$defs/Description"
        },
        "condition": {
          "$ref": "#/$defs/BranchCondition"
        },
        "steps": {
          "type": "array",
          "items": {
            "$ref": "#/$defs/Step"
          }
        }
      }
    },
    "BranchStep": {
      "allOf": [
        {
          "$ref": "#/$defs/StepBaseProps"
        },
        {
          "type": "object",
          "required": [
            "id",
            "kind",
            "description",
            "branches"
          ],
          "properties": {
            "branches": {
              "type": "array",
              "minItems": 1,
              "items": {
                "$ref": "#/$defs/Branch"
              }
            },
            "elseBranch": {
              "$ref": "#/$defs/ElseBranch"
            },
            "tryScope": {
              "type": "array",
              "items": {
                "type": "string"
              },
              "minItems": 1,
              "description": "tryCatch 分岐がガードするステップ ID の一覧。kind=tryCatch の Branch と組み合わせて try 範囲を明示する (#253)"
            },
            "kind": {
              "const": "branch"
            }
          }
        }
      ],
      "unevaluatedProperties": false
    },
    "LoopKind": {
      "type": "string",
      "enum": [
        "count",
        "condition",
        "collection"
      ]
    },
    "LoopConditionMode": {
      "type": "string",
      "enum": [
        "continue",
        "exit"
      ]
    },
    "LoopStep": {
      "allOf": [
        {
          "$ref": "#/$defs/StepBaseProps"
        },
        {
          "type": "object",
          "required": [
            "id",
            "kind",
            "description",
            "loopKind",
            "steps"
          ],
          "properties": {
            "loopKind": {
              "$ref": "#/$defs/LoopKind"
            },
            "countExpression": {
              "$ref": "common.v2.schema.json#/$defs/ExpressionString"
            },
            "conditionMode": {
              "$ref": "#/$defs/LoopConditionMode"
            },
            "conditionExpression": {
              "$ref": "common.v2.schema.json#/$defs/ExpressionString"
            },
            "collectionSource": {
              "type": "string"
            },
            "collectionItemName": {
              "type": "string"
            },
            "steps": {
              "type": "array",
              "items": {
                "$ref": "#/$defs/Step"
              }
            },
            "kind": {
              "const": "loop"
            }
          }
        }
      ],
      "unevaluatedProperties": false
    },
    "LoopBreakStep": {
      "allOf": [
        {
          "$ref": "#/$defs/StepBaseProps"
        },
        {
          "type": "object",
          "required": [
            "id",
            "kind",
            "description"
          ],
          "properties": {
            "kind": {
              "const": "loopBreak"
            }
          }
        }
      ],
      "unevaluatedProperties": false
    },
    "LoopContinueStep": {
      "allOf": [
        {
          "$ref": "#/$defs/StepBaseProps"
        },
        {
          "type": "object",
          "required": [
            "id",
            "kind",
            "description"
          ],
          "properties": {
            "kind": {
              "const": "loopContinue"
            }
          }
        }
      ],
      "unevaluatedProperties": false
    },
    "JumpStep": {
      "allOf": [
        {
          "$ref": "#/$defs/StepBaseProps"
        },
        {
          "type": "object",
          "required": [
            "id",
            "kind",
            "description",
            "jumpTo"
          ],
          "properties": {
            "jumpTo": {
              "type": "string"
            },
            "kind": {
              "const": "jump"
            }
          }
        }
      ],
      "unevaluatedProperties": false
    },
    "ComputeStep": {
      "allOf": [
        {
          "$ref": "#/$defs/StepBaseProps"
        },
        {
          "type": "object",
          "required": [
            "id",
            "kind",
            "description",
            "expression"
          ],
          "properties": {
            "expression": {
              "$ref": "common.v2.schema.json#/$defs/ExpressionString"
            },
            "kind": {
              "const": "compute"
            }
          }
        }
      ],
      "unevaluatedProperties": false
    },
    "ReturnStep": {
      "allOf": [
        {
          "$ref": "#/$defs/StepBaseProps"
        },
        {
          "type": "object",
          "required": [
            "id",
            "kind",
            "description"
          ],
          "properties": {
            "responseRef": {
              "type": "string"
            },
            "bodyExpression": {
              "$ref": "common.v2.schema.json#/$defs/ExpressionString"
            },
            "kind": {
              "const": "return"
            }
          }
        }
      ],
      "unevaluatedProperties": false
    },
    "LogStep": {
      "allOf": [
        {
          "$ref": "#/$defs/StepBaseProps"
        },
        {
          "type": "object",
          "required": [
            "id",
            "kind",
            "description",
            "level",
            "message"
          ],
          "properties": {
            "level": {
              "$ref": "#/$defs/LogLevel"
            },
            "message": {
              "type": "string"
            },
            "category": {
              "type": "string"
            },
            "structuredData": {
              "type": "object",
              "additionalProperties": {
                "type": "string"
              }
            },
            "kind": {
              "const": "log"
            }
          }
        }
      ],
      "unevaluatedProperties": false
    },
    "AuditResource": {
      "type": "object",
      "required": [
        "type",
        "id"
      ],
      "additionalProperties": false,
      "properties": {
        "type": {
          "type": "string"
        },
        "id": {
          "$ref": "common.v2.schema.json#/$defs/LocalId"
        }
      }
    },
    "AuditStep": {
      "allOf": [
        {
          "$ref": "#/$defs/StepBaseProps"
        },
        {
          "type": "object",
          "required": [
            "id",
            "kind",
            "description",
            "action"
          ],
          "properties": {
            "action": {
              "type": "string"
            },
            "resource": {
              "$ref": "#/$defs/AuditResource"
            },
            "result": {
              "$ref": "#/$defs/AuditResult"
            },
            "reason": {
              "type": "string"
            },
            "sensitive": {
              "type": "boolean"
            },
            "kind": {
              "const": "audit"
            }
          }
        }
      ],
      "unevaluatedProperties": false
    },
    "WorkflowApprover": {
      "type": "object",
      "required": [
        "role"
      ],
      "additionalProperties": false,
      "properties": {
        "role": {
          "type": "string",
          "description": "RBAC catalog role key reference"
        },
        "label": {
          "type": "string"
        },
        "order": {
          "type": "integer",
          "minimum": 1
        }
      }
    },
    "WorkflowQuorum": {
      "type": "object",
      "required": [
        "type"
      ],
      "additionalProperties": false,
      "properties": {
        "type": {
          "$ref": "#/$defs/WorkflowQuorumType"
        },
        "n": {
          "type": "integer",
          "minimum": 1
        }
      },
      "allOf": [
        {
          "if": {
            "properties": {
              "type": {
                "const": "n-of-m"
              }
            },
            "required": [
              "type"
            ]
          },
          "then": {
            "required": [
              "n"
            ]
          }
        }
      ]
    },
    "WorkflowEscalateTo": {
      "type": "object",
      "additionalProperties": false,
      "properties": {
        "role": {
          "type": "string",
          "description": "RBAC catalog role key reference"
        },
        "userExpression": {
          "$ref": "common.v2.schema.json#/$defs/ExpressionString",
          "description": "ConvCompletion expression for dynamic escalation assignee"
        }
      }
    },
    "WorkflowStep": {
      "allOf": [
        {
          "$ref": "#/$defs/StepBaseProps"
        },
        {
          "type": "object",
          "required": [
            "id",
            "kind",
            "description",
            "pattern",
            "approvers"
          ],
          "properties": {
            "pattern": {
              "$ref": "#/$defs/WorkflowPattern"
            },
            "approvers": {
              "type": "array",
              "items": {
                "$ref": "#/$defs/WorkflowApprover"
              }
            },
            "quorum": {
              "$ref": "#/$defs/WorkflowQuorum"
            },
            "onApproved": {
              "type": "array",
              "items": {
                "$ref": "#/$defs/Step"
              }
            },
            "onRejected": {
              "type": "array",
              "items": {
                "$ref": "#/$defs/Step"
              }
            },
            "onTimeout": {
              "type": "array",
              "items": {
                "$ref": "#/$defs/Step"
              }
            },
            "deadlineExpression": {
              "$ref": "common.v2.schema.json#/$defs/ExpressionString",
              "description": "ConvCompletion expression for approval deadline"
            },
            "escalateAfter": {
              "type": "string",
              "description": "Duration expression before escalation"
            },
            "escalateTo": {
              "$ref": "#/$defs/WorkflowEscalateTo"
            },
            "kind": {
              "const": "workflow"
            }
          }
        },
        {
          "if": {
            "properties": {
              "pattern": {
                "const": "approval-escalation"
              }
            },
            "required": [
              "pattern"
            ]
          },
          "then": {
            "required": [
              "escalateAfter",
              "escalateTo"
            ]
          }
        },
        {
          "if": {
            "properties": {
              "pattern": {
                "const": "approval-quorum"
              }
            },
            "required": [
              "pattern"
            ]
          },
          "then": {
            "required": [
              "quorum"
            ]
          }
        },
        {
          "if": {
            "properties": {
              "pattern": {
                "const": "ad-hoc"
              }
            },
            "required": [
              "pattern"
            ]
          },
          "then": {
            "required": [
              "description"
            ]
          }
        }
      ],
      "unevaluatedProperties": false
    },
    "OtherStep": {
      "allOf": [
        {
          "$ref": "#/$defs/StepBaseProps"
        },
        {
          "type": "object",
          "required": [
            "id",
            "kind",
            "description"
          ],
          "properties": {
            "outputSchema": {
              "type": "object",
              "additionalProperties": {
                "type": "string"
              }
            },
            "kind": {
              "oneOf": [
                {
                  "const": "other"
                },
                {
                  "type": "string",
                  "pattern": "^[a-z][a-z0-9_-]*:[A-Z][A-Za-z0-9]*$"
                }
              ]
            }
          }
        }
      ],
      "unevaluatedProperties": false
    },
    "ClosingPeriod": {
      "type": "string",
      "enum": [
        "daily",
        "monthly",
        "quarterly",
        "yearly",
        "custom"
      ]
    },
    "ClosingStep": {
      "allOf": [
        {
          "$ref": "#/$defs/StepBaseProps"
        },
        {
          "type": "object",
          "required": [
            "id",
            "kind",
            "description",
            "period"
          ],
          "properties": {
            "period": {
              "$ref": "#/$defs/ClosingPeriod"
            },
            "customCron": {
              "type": "string"
            },
            "cutoffAt": {
              "type": "string"
            },
            "idempotencyKey": {
              "type": "string"
            },
            "rollbackOnFailure": {
              "type": "boolean"
            },
            "kind": {
              "const": "closing"
            }
          }
        }
      ],
      "unevaluatedProperties": false
    },
    "CdcCaptureMode": {
      "type": "string",
      "enum": [
        "full",
        "incremental"
      ]
    },
    "CdcDestination": {
      "type": "object",
      "required": [
        "type"
      ],
      "additionalProperties": false,
      "properties": {
        "type": {
          "$ref": "#/$defs/CdcDestinationKind"
        },
        "target": {
          "type": "string"
        }
      }
    },
    "CdcStep": {
      "allOf": [
        {
          "$ref": "#/$defs/StepBaseProps"
        },
        {
          "type": "object",
          "required": [
            "id",
            "kind",
            "description",
            "tables",
            "captureMode",
            "destination"
          ],
          "properties": {
            "tables": {
              "type": "array",
              "items": {
                "type": "string"
              }
            },
            "captureMode": {
              "$ref": "#/$defs/CdcCaptureMode"
            },
            "destination": {
              "$ref": "#/$defs/CdcDestination"
            },
            "includeColumns": {
              "type": "array",
              "items": {
                "type": "string"
              }
            },
            "excludeColumns": {
              "type": "array",
              "items": {
                "type": "string"
              }
            },
            "kind": {
              "const": "cdc"
            }
          }
        }
      ],
      "unevaluatedProperties": false
    },
    "TransactionIsolationLevel": {
      "type": "string",
      "enum": [
        "READ_COMMITTED",
        "REPEATABLE_READ",
        "SERIALIZABLE"
      ]
    },
    "TransactionPropagation": {
      "type": "string",
      "enum": [
        "REQUIRED",
        "REQUIRES_NEW",
        "NESTED"
      ]
    },
    "TransactionScopeStep": {
      "description": "複数 DB 操作を 1 TX でまとめる meta-step (#415)。Power Platform Changeset / EF Core TransactionScope 由来。steps[] が atomic 単位で実行される",
      "allOf": [
        {
          "$ref": "#/$defs/StepBaseProps"
        },
        {
          "type": "object",
          "required": [
            "id",
            "kind",
            "description",
            "steps"
          ],
          "properties": {
            "isolationLevel": {
              "$ref": "#/$defs/TransactionIsolationLevel"
            },
            "propagation": {
              "$ref": "#/$defs/TransactionPropagation"
            },
            "timeoutMs": {
              "type": "number",
              "minimum": 0
            },
            "rollbackOn": {
              "description": "rollback を引き起こす errorCode の配列。ProcessFlow.errorCatalog のキー参照",
              "type": "array",
              "items": {
                "type": "string"
              }
            },
            "steps": {
              "description": "TX 内で実行する step 列。1 TX に含めたい DB / 外部呼出を順序通りに並べる",
              "type": "array",
              "items": {
                "$ref": "#/$defs/Step"
              }
            },
            "onCommit": {
              "description": "TX commit 成功後に実行する step 列 (任意)。例: 通知送信、キャッシュ無効化",
              "type": "array",
              "items": {
                "$ref": "#/$defs/Step"
              }
            },
            "onRollback": {
              "description": "TX rollback 後に実行する step 列 (任意・補償処理)。例: Stripe authorize の cancel、Slack 通知",
              "type": "array",
              "items": {
                "$ref": "#/$defs/Step"
              }
            },
            "outcomes": {
              "type": "object",
              "additionalProperties": false,
              "properties": {
                "success": {
                  "$ref": "#/$defs/ExternalCallOutcomeSpec"
                },
                "failure": {
                  "$ref": "#/$defs/ExternalCallOutcomeSpec"
                },
                "timeout": {
                  "$ref": "#/$defs/ExternalCallOutcomeSpec"
                }
              }
            },
            "kind": {
              "const": "transactionScope"
            }
          }
        }
      ],
      "unevaluatedProperties": false
    },
    "Step": {
      "oneOf": [
        {
          "$ref": "#/$defs/ValidationStep"
        },
        {
          "$ref": "#/$defs/DbAccessStep"
        },
        {
          "$ref": "#/$defs/ExternalSystemStep"
        },
        {
          "$ref": "#/$defs/CommonProcessStep"
        },
        {
          "$ref": "#/$defs/ScreenTransitionStep"
        },
        {
          "$ref": "#/$defs/DisplayUpdateStep"
        },
        {
          "$ref": "#/$defs/BranchStep"
        },
        {
          "$ref": "#/$defs/LoopStep"
        },
        {
          "$ref": "#/$defs/LoopBreakStep"
        },
        {
          "$ref": "#/$defs/LoopContinueStep"
        },
        {
          "$ref": "#/$defs/JumpStep"
        },
        {
          "$ref": "#/$defs/ComputeStep"
        },
        {
          "$ref": "#/$defs/ReturnStep"
        },
        {
          "$ref": "#/$defs/LogStep"
        },
        {
          "$ref": "#/$defs/AuditStep"
        },
        {
          "$ref": "#/$defs/WorkflowStep"
        },
        {
          "$ref": "#/$defs/TransactionScopeStep"
        },
        {
          "$ref": "#/$defs/EventPublishStep"
        },
        {
          "$ref": "#/$defs/EventSubscribeStep"
        },
        {
          "$ref": "#/$defs/ClosingStep"
        },
        {
          "$ref": "#/$defs/CdcStep"
        },
        {
          "$ref": "#/$defs/OtherStep"
        }
      ]
    },
    "ProcessFlowKind": {
      "type": "string",
      "enum": [
        "screen",
        "batch",
        "scheduled",
        "system",
        "common",
        "other"
      ]
    },
    "StepKind": {
      "type": "string",
      "enum": [
        "validation",
        "dbAccess",
        "externalSystem",
        "commonProcess",
        "screenTransition",
        "displayUpdate",
        "branch",
        "loop",
        "loopBreak",
        "loopContinue",
        "jump",
        "compute",
        "return",
        "log",
        "audit",
        "workflow",
        "transactionScope",
        "eventPublish",
        "eventSubscribe",
        "closing",
        "cdc",
        "other"
      ]
    },
    "LogLevel": {
      "type": "string",
      "enum": [
        "trace",
        "debug",
        "info",
        "warn",
        "error"
      ]
    },
    "WorkflowQuorumType": {
      "type": "string",
      "enum": [
        "all",
        "any",
        "majority",
        "n-of-m"
      ]
    },
    "HealthCheckKind": {
      "type": "string",
      "enum": [
        "db",
        "http",
        "custom"
      ]
    },
    "CdcDestinationKind": {
      "type": "string",
      "enum": [
        "auditLog",
        "eventStream",
        "table"
      ]
    },
    "MarkerKind": {
      "type": "string",
      "enum": [
        "chat",
        "attention",
        "todo",
        "question"
      ]
    },
    "AuditResult": {
      "type": "string",
      "enum": [
        "success",
        "failure"
      ]
    },
    "MarkerAuthor": {
      "type": "string",
      "enum": [
        "human",
        "ai"
      ]
    }
  },
  "title": "ProcessFlow v2 (処理フロー)",
  "description": "html-designer v2 の処理フロー (ProcessFlow) の正規 JSON Schema。v1 schema から discriminator・union・命名を再設計。"
}