{
  "$schema": "https://json-schema.org/draft/2020-12/schema",
  "$id": "https://raw.githubusercontent.com/csilost2001/html-designer/main/schemas/v2/screen-item.v2.schema.json",
  "title": "ScreenItem — 画面項目定義 v2",
  "description": "画面 (GrapesJS) のフォーム要素に紐付けるバリデーション・ラベル・表示制御を宣言的に保持するファイル定義。data/screen-items/{screenId}.json に 1 画面 = 1 ファイルで配置する。",
  "$ref": "#/$defs/ScreenItemsFile",
  "$defs": {
    "FieldType": {
      "description": "画面項目の入出力値の型。process-flow.v2.schema.json の FieldType と同等の型セットを独立定義する (相互参照による運用複雑化を避けるため)。",
      "oneOf": [
        {
          "description": "プリミティブ型 (文字列 / 数値 / 真偽値 / 日付 / 時刻 / ファイル / 選択肢)。",
          "type": "string",
          "enum": [
            "string",
            "number",
            "boolean",
            "date",
            "datetime",
            "time",
            "file",
            "select",
            "multiselect"
          ]
        },
        {
          "description": "カスタム型 (業界・業態固有の拡張フィールド型)。",
          "type": "object",
          "required": ["kind", "label"],
          "additionalProperties": false,
          "properties": {
            "kind": {
              "type": "string",
              "const": "custom",
              "description": "カスタム型の discriminator。値は固定 'custom'。"
            },
            "label": {
              "type": "string",
              "description": "カスタム型の表示名 (例: 「郵便番号」「電話番号」)。"
            }
          }
        }
      ]
    },
    "DirectionKind": {
      "description": "画面項目の方向性。input = フォーム入力 (デフォルト) / output = データ表示専用。",
      "type": "string",
      "enum": ["input", "output"]
    },
    "ValueSourceFlowVariable": {
      "description": "処理フロー変数を出力項目のバインド元とするバリアント。",
      "type": "object",
      "required": ["kind", "variableName"],
      "additionalProperties": false,
      "properties": {
        "kind": {
          "type": "string",
          "const": "flowVariable",
          "description": "バインド元種別の discriminator。値は固定 'flowVariable'。"
        },
        "processFlowId": {
          "$ref": "common.v2.schema.json#/$defs/Uuid",
          "description": "参照する処理フローの ID。省略時は同一画面に紐付く処理フローを暗黙参照する。"
        },
        "variableName": {
          "$ref": "common.v2.schema.json#/$defs/BusinessIdentifier",
          "description": "バインドする処理フロー変数名 (lowerCamelCase)。"
        }
      }
    },
    "ValueSourceTableColumn": {
      "description": "テーブルカラムを出力項目のバインド元とするバリアント。",
      "type": "object",
      "required": ["kind", "tableName", "columnName"],
      "additionalProperties": false,
      "properties": {
        "kind": {
          "type": "string",
          "const": "tableColumn",
          "description": "バインド元種別の discriminator。値は固定 'tableColumn'。"
        },
        "tableName": {
          "$ref": "common.v2.schema.json#/$defs/DbTableName",
          "description": "参照するテーブルの物理名。"
        },
        "columnName": {
          "$ref": "common.v2.schema.json#/$defs/DbColumnName",
          "description": "参照するカラムの物理名。"
        }
      }
    },
    "ValueSourceViewColumn": {
      "description": "ビュー列を出力項目のバインド元とするバリアント。",
      "type": "object",
      "required": ["kind", "viewName", "columnName"],
      "additionalProperties": false,
      "properties": {
        "kind": {
          "type": "string",
          "const": "viewColumn",
          "description": "バインド元種別の discriminator。値は固定 'viewColumn'。"
        },
        "viewName": {
          "$ref": "common.v2.schema.json#/$defs/BusinessIdentifier",
          "description": "参照するビューの識別名 (lowerCamelCase)。"
        },
        "columnName": {
          "$ref": "common.v2.schema.json#/$defs/BusinessIdentifier",
          "description": "参照するビュー列の名前。"
        }
      }
    },
    "ValueSourceExpression": {
      "description": "計算式を出力項目のバインド元とするバリアント。",
      "type": "object",
      "required": ["kind", "expression"],
      "additionalProperties": false,
      "properties": {
        "kind": {
          "type": "string",
          "const": "expression",
          "description": "バインド元種別の discriminator。値は固定 'expression'。"
        },
        "expression": {
          "$ref": "common.v2.schema.json#/$defs/ExpressionString",
          "description": "計算式 (例: '= @quantity * @unitPrice')。式言語の詳細は process-flow-expression-language.md を参照。"
        }
      }
    },
    "ValueSource": {
      "description": "出力項目 (direction='output') のバインド元の discriminated union。kind フィールドで 4 種別を識別する。",
      "oneOf": [
        { "$ref": "#/$defs/ValueSourceFlowVariable" },
        { "$ref": "#/$defs/ValueSourceTableColumn" },
        { "$ref": "#/$defs/ValueSourceViewColumn" },
        { "$ref": "#/$defs/ValueSourceExpression" }
      ]
    },
    "ScreenItemSelectOption": {
      "description": "選択肢型 (select / multiselect) の 1 選択肢定義。",
      "type": "object",
      "required": ["value", "label"],
      "additionalProperties": false,
      "properties": {
        "value": {
          "type": "string",
          "description": "選択肢の値 (送信値)。"
        },
        "label": {
          "type": "string",
          "description": "選択肢の表示名 (日本語可)。"
        }
      }
    },
    "ScreenItemErrorMessages": {
      "description": "バリデーションエラーメッセージのカスタム定義。named キー (required / minLength / maxLength / invalidFormat / outOfRange) 以外の業務独自エラーコードも additionalProperties として受け付ける。",
      "type": "object",
      "additionalProperties": {
        "type": "string",
        "description": "エラーコードに対応するカスタムエラーメッセージ。"
      },
      "properties": {
        "required": {
          "type": "string",
          "description": "必須エラー時のメッセージ。例: 「{label}は必須です」。"
        },
        "minLength": {
          "type": "string",
          "description": "最小文字数違反時のメッセージ。"
        },
        "maxLength": {
          "type": "string",
          "description": "最大文字数超過時のメッセージ。"
        },
        "invalidFormat": {
          "type": "string",
          "description": "フォーマット不正時のメッセージ。"
        },
        "outOfRange": {
          "type": "string",
          "description": "値が範囲外の場合のメッセージ。"
        }
      }
    },
    "ScreenItem": {
      "description": "画面項目 1 件の定義。フォーム制御・バリデーション制約・表示制御・バインド元を一元管理する。",
      "type": "object",
      "required": ["id", "label", "kind"],
      "additionalProperties": false,
      "properties": {
        "id": {
          "$ref": "common.v2.schema.json#/$defs/BusinessIdentifier",
          "description": "業務識別子 (lowerCamelCase 強制)。実装コードのフィールド名 / API キーと対応する。例: userName, postalCode。GrapesJS の data-item-id と一致させる。"
        },
        "label": {
          "type": "string",
          "minLength": 1,
          "description": "日本語表示名。エラーメッセージの {label} プレースホルダに展開される。"
        },
        "kind": {
          "$ref": "#/$defs/FieldType",
          "description": "項目の型。文字列 / 数値 / 真偽値 / 日付など。"
        },
        "required": {
          "type": "boolean",
          "description": "必須入力かどうか。"
        },
        "readonly": {
          "type": "boolean",
          "description": "読み取り専用かどうか。フォームでは表示されるが変更不可。"
        },
        "disabled": {
          "type": "boolean",
          "description": "無効状態かどうか。フォームでは非活性表示。"
        },
        "minLength": {
          "type": "integer",
          "minimum": 0,
          "description": "文字列型の最小文字数制約。"
        },
        "maxLength": {
          "type": "integer",
          "minimum": 1,
          "description": "文字列型の最大文字数制約。"
        },
        "pattern": {
          "type": "string",
          "description": "正規表現パターン。直接パターン文字列または @conv.regex.* 参照 (例: @conv.regex.email)。"
        },
        "min": {
          "type": "number",
          "description": "数値型の最小値制約。"
        },
        "max": {
          "type": "number",
          "description": "数値型の最大値制約。"
        },
        "step": {
          "type": "number",
          "description": "数値型のステップ値 (増減単位)。"
        },
        "options": {
          "type": "array",
          "items": { "$ref": "#/$defs/ScreenItemSelectOption" },
          "description": "選択肢リスト。select / multiselect 型で使用。"
        },
        "defaultValue": {
          "oneOf": [
            { "type": "string" },
            { "type": "number" },
            { "type": "boolean" }
          ],
          "description": "フォームの初期値。型は kind に応じた適切な型を使用する。"
        },
        "placeholder": {
          "type": "string",
          "description": "入力欄のプレースホルダテキスト。"
        },
        "helperText": {
          "type": "string",
          "description": "入力欄下部に表示するヘルプテキスト。"
        },
        "errorMessages": {
          "$ref": "#/$defs/ScreenItemErrorMessages",
          "description": "バリデーションエラーメッセージのカスタム定義。未定義の場合は規約カタログのデフォルトメッセージを使用する。"
        },
        "visibleWhen": {
          "$ref": "common.v2.schema.json#/$defs/ExpressionString",
          "description": "表示制御式。式が true の場合に項目を表示する。例: '@orderType == \"domestic\"'。"
        },
        "enabledWhen": {
          "$ref": "common.v2.schema.json#/$defs/ExpressionString",
          "description": "活性制御式。式が true の場合に項目を活性 (編集可) にする。"
        },
        "direction": {
          "$ref": "#/$defs/DirectionKind",
          "description": "画面上での役割。省略時は 'input' (フォーム入力) として扱う。"
        },
        "displayFormat": {
          "type": "string",
          "description": "出力項目 (direction='output') の表示書式。例: 'YYYY/MM/DD', '¥#,##0', '0.00%'。"
        },
        "valueFrom": {
          "$ref": "#/$defs/ValueSource",
          "description": "出力項目 (direction='output') のバインド元。どのデータを表示するかを指定する。"
        },
        "computed": {
          "$ref": "common.v2.schema.json#/$defs/ExpressionString",
          "description": "派生値の計算式。'= ' で始まる式文字列 (例: '= @quantity * @unitPrice')。direction='output' で計算結果をバインドする際に使用する。"
        },
        "description": {
          "$ref": "common.v2.schema.json#/$defs/Description",
          "description": "画面項目の補足説明。業務ルール・実装上の注意点を記述する。"
        }
      }
    },
    "ScreenItemsFile": {
      "description": "画面項目定義ファイルの root。1 画面 = 1 ファイル (data/screen-items/{screenId}.json)。",
      "type": "object",
      "required": ["screenId", "version", "updatedAt", "items"],
      "additionalProperties": false,
      "properties": {
        "$schema": {
          "type": "string",
          "description": "JSON Schema URL (IDE 関連付け用)。"
        },
        "screenId": {
          "$ref": "common.v2.schema.json#/$defs/Uuid",
          "description": "紐付く画面の ID (ScreenNode.id と一致する)。"
        },
        "version": {
          "$ref": "common.v2.schema.json#/$defs/SemVer",
          "description": "定義ファイルのバージョン (SemVer)。"
        },
        "updatedAt": {
          "$ref": "common.v2.schema.json#/$defs/Timestamp",
          "description": "最終更新日時 (ISO 8601 UTC)。"
        },
        "items": {
          "type": "array",
          "items": { "$ref": "#/$defs/ScreenItem" },
          "description": "画面項目定義のリスト。id でユニーク。"
        }
      }
    }
  }
}
