{
  "$schema": "../../../../schemas/v3/screen.v3.schema.json",
  "id": "e3a7d690-4021-41bd-92c7-440e320de37e",
  "name": "振込実行",
  "description": "顧客が振込先口座と金額を指定して振込を実行する画面。100万円超は承認待ちステータスに遷移し、結果は別画面 (or 通知) で表示。",
  "version": "1.0.0",
  "maturity": "committed",
  "createdAt": "2026-04-28T00:00:00.000Z",
  "updatedAt": "2026-04-28T00:00:00.000Z",
  "kind": "form",
  "path": "/finance/transfers/new",
  "auth": "required",
  "items": [
    {
      "id": "fromAccountNumber",
      "label": "振込元口座番号",
      "type": { "kind": "extension", "extensionRef": "finance:accountNumber" },
      "direction": "input",
      "required": true,
      "pattern": "@conv.regex.account-number",
      "errorMessages": {
        "required": "@conv.msg.fromAccount.required",
        "invalidFormat": "@conv.msg.accountNumber.invalidFormat"
      }
    },
    {
      "id": "toAccountNumber",
      "label": "振込先口座番号",
      "type": { "kind": "extension", "extensionRef": "finance:accountNumber" },
      "direction": "input",
      "required": true,
      "pattern": "@conv.regex.account-number",
      "errorMessages": {
        "required": "@conv.msg.toAccount.required",
        "invalidFormat": "@conv.msg.accountNumber.invalidFormat"
      }
    },
    {
      "id": "amount",
      "label": "振込額",
      "type": { "kind": "extension", "extensionRef": "finance:transferAmount" },
      "direction": "input",
      "required": true,
      "min": 1,
      "max": 99999999,
      "displayFormat": "¥#,##0",
      "errorMessages": {
        "required": "@conv.msg.amount.required",
        "outOfRange": "@conv.msg.amount.outOfRange"
      }
    },
    {
      "id": "memo",
      "label": "メモ",
      "type": "string",
      "direction": "input",
      "required": false,
      "maxLength": 200
    },
    {
      "id": "fromAccountBalance",
      "label": "振込元残高",
      "type": "integer",
      "direction": "output",
      "displayFormat": "¥#,##0",
      "valueFrom": {
        "kind": "tableColumn",
        "ref": {
          "tableId": "3d37919f-fddb-4ebb-a742-74d3ab76e593",
          "columnId": "col-a06"
        }
      }
    },
    {
      "id": "fee",
      "label": "手数料",
      "type": "integer",
      "direction": "output",
      "displayFormat": "¥#,##0",
      "valueFrom": {
        "kind": "expression",
        "expression": "@fn.calculateTransferFee(@inputs.fromAccountNumber, @inputs.toAccountNumber, @inputs.amount)"
      }
    },
    {
      "id": "approvalRequired",
      "label": "承認必要",
      "type": "boolean",
      "direction": "output",
      "valueFrom": {
        "kind": "expression",
        "expression": "@inputs.amount >= @conv.limit.highValueTransferThreshold"
      },
      "helperText": "100 万円以上は管理職 3 段承認が必要です。"
    }
  ],
  "design": { "designFileRef": "design.json" },
  "authoring": {
    "glossary": {
      "振込": {
        "definition": "口座 A から口座 B へ資金を移動する業務操作。同一銀行内 / 他行 (FX) で扱いが異なるが、本サンプルは同一銀行内のみ。",
        "aliases": ["Transfer", "送金"]
      },
      "高額振込": {
        "definition": "1 件 1,000,000 JPY 以上の振込。マネロン規制 + 内部統制の観点から 3 段承認 (担当 / 課長 / 部長) を必要とする。",
        "aliases": ["High-Value Transfer"]
      }
    }
  }
}
