{
  "dataSources": [],
  "assets": [],
  "styles": [],
  "pages": [
    {
      "frames": [
        {
          "component": {
            "type": "wrapper",
            "stylable": [
              "background",
              "background-color",
              "background-image",
              "background-repeat",
              "background-attachment",
              "background-position",
              "background-size"
            ],
            "head": {
              "type": "head"
            },
            "docEl": {
              "tagName": "html"
            },
            "components": "<div>\n  <nav class=\"navbar navbar-dark px-3 py-2\" style=\"background:#6366f1\">\n    <span class=\"navbar-brand mb-0 fw-bold small\"><i class=\"bi bi-building me-2\"></i>顧客管理システム</span>\n    <span class=\"text-white small\">管理者 様</span>\n  </nav>\n  <div class=\"container-fluid px-3 pt-3\">\n    <div class=\"d-flex justify-content-between align-items-center mb-3\">\n      <h6 class=\"mb-0 fw-bold\"><i class=\"bi bi-people me-2 text-primary\"></i>顧客一覧</h6>\n      <button class=\"btn btn-primary btn-sm\"><i class=\"bi bi-plus-lg me-1\"></i>新規登録</button>\n    </div>\n    <div class=\"card mb-3 border-0 shadow-sm\">\n      <div class=\"card-body py-2 px-3\">\n        <div class=\"row g-2 align-items-end\">\n          <div class=\"col\">\n            <label class=\"form-label mb-1 small\">顧客名</label>\n            <input type=\"text\" class=\"form-control form-control-sm\" placeholder=\"例：山田\" name=\"keyword\" id=\"keyword\" data-item-id=\"11000003-0001-4000-8000-aaaaaaaaaaaa\">\n          </div>\n          <div class=\"col\">\n            <label class=\"form-label mb-1 small\">電話番号</label>\n            <input type=\"text\" class=\"form-control form-control-sm\" placeholder=\"例：03-1234\" name=\"phone\" id=\"phone\" data-item-id=\"11000003-0002-4000-8000-aaaaaaaaaaaa\">\n          </div>\n          <div class=\"col\">\n            <label class=\"form-label mb-1 small\">メールアドレス</label>\n            <input type=\"text\" class=\"form-control form-control-sm\" placeholder=\"例：@example.com\" name=\"email\" id=\"email\" data-item-id=\"11000003-0003-4000-8000-aaaaaaaaaaaa\">\n          </div>\n          <div class=\"col-auto\">\n            <button class=\"btn btn-primary btn-sm\"><i class=\"bi bi-search me-1\"></i>検索</button>\n          </div>\n          <div class=\"col-auto\">\n            <button class=\"btn btn-outline-secondary btn-sm\">クリア</button>\n          </div>\n        </div>\n      </div>\n    </div>\n    <div class=\"card border-0 shadow-sm\">\n      <div class=\"card-body p-0\">\n        <table class=\"table table-sm table-hover mb-0 align-middle\">\n          <thead class=\"table-light\">\n            <tr>\n              <th class=\"ps-3\" style=\"width:80px\">顧客ID</th>\n              <th>顧客名</th>\n              <th>フリガナ</th>\n              <th>電話番号</th>\n              <th>メールアドレス</th>\n              <th style=\"width:80px\"></th>\n            </tr>\n          </thead>\n          <tbody>\n            <tr>\n              <td class=\"ps-3 text-muted small\">C-0001</td>\n              <td class=\"fw-medium\">山田 太郎</td>\n              <td class=\"text-muted small\">ヤマダ タロウ</td>\n              <td class=\"small\">03-1234-5678</td>\n              <td class=\"small\">yamada@example.com</td>\n              <td><button class=\"btn btn-outline-primary btn-sm py-0 px-2\">詳細</button></td>\n            </tr>\n            <tr>\n              <td class=\"ps-3 text-muted small\">C-0002</td>\n              <td class=\"fw-medium\">佐藤 花子</td>\n              <td class=\"text-muted small\">サトウ ハナコ</td>\n              <td class=\"small\">06-9876-5432</td>\n              <td class=\"small\">sato@example.com</td>\n              <td><button class=\"btn btn-outline-primary btn-sm py-0 px-2\">詳細</button></td>\n            </tr>\n            <tr>\n              <td class=\"ps-3 text-muted small\">C-0003</td>\n              <td class=\"fw-medium\">鈴木 一郎</td>\n              <td class=\"text-muted small\">スズキ イチロウ</td>\n              <td class=\"small\">045-111-2222</td>\n              <td class=\"small\">suzuki@example.com</td>\n              <td><button class=\"btn btn-outline-primary btn-sm py-0 px-2\">詳細</button></td>\n            </tr>\n            <tr>\n              <td class=\"ps-3 text-muted small\">C-0004</td>\n              <td class=\"fw-medium\">田中 美咲</td>\n              <td class=\"text-muted small\">タナカ ミサキ</td>\n              <td class=\"small\">052-333-4444</td>\n              <td class=\"small\">tanaka@example.com</td>\n              <td><button class=\"btn btn-outline-primary btn-sm py-0 px-2\">詳細</button></td>\n            </tr>\n            <tr>\n              <td class=\"ps-3 text-muted small\">C-0005</td>\n              <td class=\"fw-medium\">伊藤 健太</td>\n              <td class=\"text-muted small\">イトウ ケンタ</td>\n              <td class=\"small\">011-555-6666</td>\n              <td class=\"small\">ito@example.com</td>\n              <td><button class=\"btn btn-outline-primary btn-sm py-0 px-2\">詳細</button></td>\n            </tr>\n          </tbody>\n        </table>\n      </div>\n    </div>\n    <div class=\"d-flex justify-content-between align-items-center mt-2\">\n      <small class=\"text-muted\">全 5 件</small>\n      <nav><ul class=\"pagination pagination-sm mb-0\">\n        <li class=\"page-item disabled\"><a class=\"page-link py-1\">«</a></li>\n        <li class=\"page-item active\"><a class=\"page-link py-1\">1</a></li>\n        <li class=\"page-item\"><a class=\"page-link py-1\">2</a></li>\n        <li class=\"page-item\"><a class=\"page-link py-1\">»</a></li>\n      </ul></nav>\n    </div>\n  </div>\n</div>"
          },
          "id": "fr-custlist-0003"
        }
      ],
      "type": "main",
      "id": "pg-custlist-0003"
    }
  ],
  "symbols": []
}